{
  "title": "Crossback Chair Protective Cover",
  "sku": "XBCCOVER",
  "brand": "Titan Event Furniture™",
  "price": "$3.49",
  "features": [
    "Protective Chair Covers for Crossback Chairs",
    "Protect your investment with covers for your cross back chairs."
  ],
  "specifications": {
    "UPC": "810171063229",
    "Free Shipping Deal Type": "Free Shipping Over $99",
    "Can ship FedEx?": "Yes",
    "Country of Manufacture": "China",
    "Brand": "Titan Event Furniture™",
    "Color": "Black",
    "Commercial-Grade?": "Yes",
    "Ships Assembled?": "Yes",
    "California Residents": "Click here for Proposition 65 warning"
  },
  "faq": [],
  "defaultColor": null,
  "defaultGallery": [
    "https://www.eventstable.com/media/catalog/product/d/s/dsc_0113_2.jpg",
    "https://www.eventstable.com/media/catalog/product/d/s/dsc_0116_2.jpg",
    "https://www.eventstable.com/media/catalog/product/d/s/dsc_0115_2.jpg",
    "https://www.eventstable.com/media/catalog/product/d/s/dsc_0114_2.jpg",
    "https://www.eventstable.com/media/catalog/product/d/s/dsc_0112_2.jpg",
    "https://www.eventstable.com/media/catalog/product/e/s/es9301_folded.png"
  ],
  "colors": []
}