{
  "title": "Crown Back Banquet Chair - Gold Frame with Beige Patterned Vinyl",
  "sku": "CBC9GFBPF",
  "brand": "Titan Event Furniture™",
  "price": "$48.99",
  "features": [
    "Ornate crown back design with an upscale, formal aesthetic",
    "Beige Patterned vinyl upholstery with subtle texture and warmth",
    "Gold frame finish ideal for weddings, galas, and formal celebrations",
    "15.7\" x 15.4\" seat size for comfortable, well-proportioned seating",
    "Lightweight at 14 lbs for fast, low-effort setup and breakdown",
    "Stackable construction for space-efficient storage and transport",
    "Suited for rental inventory, event venues, and hospitality use"
  ],
  "specifications": {
    "Free Shipping Deal Type": "Free Shipping on Tables and Chairs Over $5k, Free Shipping on 50 or more",
    "Can ship FedEx?": "Yes",
    "Brand": "Titan Event Furniture™",
    "Color": "Beige Patterned",
    "Back Style": "Crown Back",
    "Frame Color": "Gold Frame",
    "Upholstery Type": "Vinyl",
    "Commercial-Grade?": "Yes",
    "Overall Height": "35''",
    "Overall Width": "17.5''",
    "Seat Height": "18.9''",
    "Seat Size": "15.7'' x 15.4''",
    "Ships Assembled?": "Yes",
    "Stackable?": "Yes",
    "Item Weight": "14 lbs.",
    "California Residents": "Click here for Proposition 65 warning"
  },
  "faq": [],
  "defaultColor": null,
  "defaultGallery": [
    "https://www.eventstable.com/media/catalog/product/c/b/cbbcs-9-v4-3.jpg",
    "https://www.eventstable.com/media/catalog/product/c/b/cbbcs-9-v4-1.jpg",
    "https://www.eventstable.com/media/catalog/product/c/b/cbbcs-9-v4-5.jpg",
    "https://www.eventstable.com/media/catalog/product/c/b/cbbcs-9-v4-4_1.jpg"
  ],
  "colors": []
}