{
  "title": "6' x 30'' Solid Pine Folding Kids Farm Table",
  "sku": "KFT26-3072FLD",
  "brand": "Titan Event Furniture™",
  "price": "$441.49",
  "features": [
    "Our 6' x 30'' Kids Folding Farm Table is virtually the same as our popular 8' x 40'' Solid Pine Folding Farm Table, but downsized so the kids at the party can also get in on the action.",
    "Shipping fully assembled, This children's folding farm table arrives with a smooth, beautiful pine top finish that gives way to sturdy, durable folding legs that seamlessly lock into place, supported by steel black folding bars and a pin.",
    "Why add only one of these tables to your inventory?",
    "Free shipping is included when you purchase 10+ or combine with a chair and table order over 2k!"
  ],
  "specifications": {
    "Special Order Item": "No",
    "UPC": "810171061706",
    "Free Shipping Deal Type": "Free Shipping on Tables and Chairs Over $5k, Free Shipping on 10 or more",
    "Can ship FedEx?": "No",
    "Country of Manufacture": "China",
    "Brand": "Titan Event Furniture™",
    "Color": "Medium Rustic",
    "Material": "Pinewood",
    "Shape": "Rectangle",
    "Size": "6' x 30''",
    "Commercial-Grade?": "Yes",
    "Legs": "2.75'' Thick",
    "Overall Length / Depth": "72''",
    "Overall Height": "20.5''",
    "Overall Width": "30''",
    "Ships Assembled?": "Yes",
    "Item Weight": "59 lbs.",
    "California Residents": "Click here for Proposition 65 warning"
  },
  "faq": [],
  "defaultColor": null,
  "defaultGallery": [
    "https://www.eventstable.com/media/catalog/product/k/i/kids-solid-pine-folding-farm-table-2_2.jpg",
    "https://www.eventstable.com/media/catalog/product/k/i/kids-solid-pine-folding-farm-table-1_1.jpg",
    "https://www.eventstable.com/media/catalog/product/k/i/kids-solid-pine-folding-farm-table-3_1.jpg",
    "https://www.eventstable.com/media/catalog/product/i/m/img_4164_1.jpg",
    "https://www.eventstable.com/media/catalog/product/i/m/img_4165_1.jpg",
    "https://www.eventstable.com/media/catalog/product/i/m/img_4166_1.jpg",
    "https://www.eventstable.com/media/catalog/product/i/m/img_4167_1.jpg",
    "https://www.eventstable.com/media/catalog/product/i/m/img_4174_1.jpg",
    "https://www.eventstable.com/media/catalog/product/i/m/img_4181_1.jpg",
    "https://www.eventstable.com/media/catalog/product/i/m/img_4191_1.jpg"
  ],
  "colors": []
}